syszuxav/__init__.py
syszuxav/syszuxav.cpython-35m-x86_64-linux-gnu.so
syszuxav/syszuxav.so
syszuxav-0.1.0.dist-info/DESCRIPTION.rst
syszuxav-0.1.0.dist-info/METADATA
syszuxav-0.1.0.dist-info/RECORD
syszuxav-0.1.0.dist-info/WHEEL
syszuxav-0.1.0.dist-info/metadata.json
syszuxav-0.1.0.dist-info/top_level.txt
