Metadata-Version: 2.0
Name: syszuxav
Version: 0.1.0
Summary: python bindings for ffmpeg
Home-page: https://github.com/CivilNet/SYSZUXav
Author: Gemfield
Author-email: gemfield@civilnet.cn
License: UNKNOWN
Download-URL: https://github.com/CivilNet/SYSZUXav/releases/download/v0.1/syszuxav-0.1.0.tar.gz
Keywords: ffmpeg python
Platform: UNKNOWN
Classifier: Programming Language :: Python
Classifier: Programming Language :: Python :: 2
Classifier: Programming Language :: Python :: 3.5
Classifier: Topic :: Software Development :: Libraries
Requires-Dist: opencv-python
Requires-Dist: numpy
